pysilero/__init__.py
pysilero/cli.py
pysilero/frame_queue.py
pysilero/pickable_session.py
pysilero/pysilero.py
pysilero/utils.py
pysilero-0.1.2.dist-info/licenses/LICENSE
pysilero-0.1.2.dist-info/METADATA
pysilero-0.1.2.dist-info/WHEEL
pysilero-0.1.2.dist-info/entry_points.txt
pysilero-0.1.2.dist-info/top_level.txt
pysilero-0.1.2.dist-info/RECORD
